{
    "arquivo": "E-n51-k5",
    "media_distancia": 590.3300797017012,
    "desvio_padrao_distancia": 23.78134549289601,
    "minimo_distancia": 549.9458645128586,
    "maximo_distancia": 630.0061661529935,
    "media_tempo": 112.49456442594528,
    "desvio_padrao_tempo": 2.9855040318038197,
    "execucao_melhor_rota": 14,
    "capacidade_veiculo": 160,
    "resultados_execucoes": [
        {
            "execucao": 1,
            "distancia": 563.168420016341,
            "rota": [
                1,
                2,
                23,
                4,
                37,
                36,
                21,
                33,
                13,
                38,
                18,
                43,
                1,
                42,
                41,
                20,
                14,
                26,
                25,
                54,
                50,
                48,
                5,
                1,
                45,
                34,
                46,
                16,
                11,
                31,
                35,
                10,
                47,
                40,
                12,
                1,
                3,
                30,
                22,
                51,
                17,
                39,
                6,
                19,
                1,
                28,
                49,
                9,
                29,
                32,
                27,
                8,
                24,
                54,
                15,
                7,
                1,
                44,
                1
            ],
            "tempo_execucao": 112.26277494430542,
            "carga_por_rota": [
                148,
                156,
                158,
                146,
                158,
                11
            ]
        },
        {
            "execucao": 2,
            "distancia": 601.8839377739218,
            "rota": [
                1,
                25,
                44,
                8,
                24,
                49,
                9,
                57,
                33,
                23,
                13,
                1,
                4,
                47,
                38,
                16,
                46,
                34,
                40,
                31,
                11,
                45,
                43,
                20,
                1,
                42,
                41,
                28,
                27,
                32,
                29,
                36,
                37,
                30,
                22,
                35,
                51,
                1,
                10,
                50,
                21,
                7,
                15,
                26,
                1,
                19,
                18,
                5,
                48,
                14,
                53,
                2,
                3,
                17,
                1,
                39,
                6,
                12,
                1
            ],
            "tempo_execucao": 113.5477204322815,
            "carga_por_rota": [
                145,
                149,
                154,
                121,
                153,
                55
            ]
        },
        {
            "execucao": 3,
            "distancia": 575.1213057118445,
            "rota": [
                1,
                13,
                38,
                45,
                46,
                34,
                16,
                18,
                48,
                47,
                1,
                19,
                7,
                15,
                24,
                8,
                25,
                54,
                44,
                49,
                2,
                1,
                33,
                28,
                26,
                14,
                42,
                41,
                20,
                43,
                5,
                1,
                9,
                27,
                32,
                29,
                4,
                36,
                37,
                21,
                30,
                3,
                1,
                23,
                12,
                39,
                10,
                51,
                17,
                22,
                11,
                40,
                31,
                50,
                1,
                6,
                35,
                1
            ],
            "tempo_execucao": 114.39488124847412,
            "carga_por_rota": [
                130,
                157,
                143,
                158,
                142,
                47
            ]
        },
        {
            "execucao": 4,
            "distancia": 574.4775989563406,
            "rota": [
                1,
                18,
                45,
                38,
                16,
                46,
                43,
                20,
                42,
                52,
                14,
                5,
                48,
                1,
                41,
                33,
                28,
                49,
                7,
                25,
                15,
                26,
                1,
                19,
                9,
                13,
                56,
                50,
                39,
                17,
                51,
                22,
                1,
                30,
                3,
                12,
                35,
                2,
                23,
                4,
                21,
                36,
                1,
                37,
                29,
                27,
                8,
                44,
                24,
                54,
                47,
                32,
                57,
                6,
                11,
                34,
                40,
                1,
                31,
                10,
                1
            ],
            "tempo_execucao": 110.36792945861816,
            "carga_por_rota": [
                154,
                125,
                159,
                157,
                152,
                30
            ]
        },
        {
            "execucao": 5,
            "distancia": 630.0061661529935,
            "rota": [
                1,
                13,
                14,
                20,
                43,
                55,
                50,
                31,
                35,
                12,
                1,
                25,
                47,
                6,
                56,
                17,
                22,
                51,
                10,
                39,
                11,
                34,
                46,
                16,
                45,
                1,
                38,
                40,
                19,
                53,
                5,
                42,
                41,
                18,
                48,
                1,
                26,
                15,
                7,
                49,
                33,
                23,
                32,
                9,
                28,
                1,
                44,
                24,
                8,
                27,
                29,
                4,
                36,
                21,
                30,
                1,
                3,
                2,
                37,
                1
            ],
            "tempo_execucao": 115.3111035823822,
            "carga_por_rota": [
                156,
                159,
                135,
                150,
                134,
                43
            ]
        },
        {
            "execucao": 6,
            "distancia": 581.4611914918564,
            "rota": [
                1,
                47,
                39,
                10,
                40,
                11,
                31,
                35,
                51,
                17,
                59,
                22,
                30,
                12,
                1,
                50,
                33,
                3,
                23,
                4,
                36,
                37,
                21,
                29,
                32,
                1,
                6,
                48,
                5,
                42,
                52,
                41,
                20,
                43,
                45,
                38,
                46,
                16,
                18,
                1,
                34,
                7,
                15,
                53,
                19,
                26,
                25,
                44,
                1,
                49,
                14,
                53,
                28,
                24,
                8,
                27,
                9,
                2,
                13,
                1
            ],
            "tempo_execucao": 111.36220598220825,
            "carga_por_rota": [
                153,
                160,
                159,
                149,
                156
            ]
        },
        {
            "execucao": 7,
            "distancia": 621.1915739751216,
            "rota": [
                1,
                5,
                43,
                20,
                42,
                41,
                14,
                49,
                8,
                24,
                7,
                1,
                28,
                2,
                36,
                21,
                33,
                56,
                35,
                18,
                38,
                45,
                46,
                16,
                1,
                34,
                11,
                40,
                31,
                51,
                22,
                30,
                17,
                59,
                10,
                37,
                60,
                48,
                1,
                26,
                15,
                25,
                44,
                23,
                29,
                32,
                27,
                9,
                4,
                1,
                13,
                6,
                50,
                39,
                12,
                3,
                47,
                1,
                19,
                1
            ],
            "tempo_execucao": 112.55947184562683,
            "carga_por_rota": [
                155,
                153,
                142,
                149,
                137,
                41
            ]
        },
        {
            "execucao": 8,
            "distancia": 616.0245678440223,
            "rota": [
                1,
                39,
                50,
                11,
                40,
                31,
                59,
                36,
                37,
                4,
                29,
                32,
                27,
                1,
                14,
                18,
                5,
                19,
                26,
                25,
                24,
                8,
                1,
                7,
                49,
                44,
                9,
                23,
                12,
                3,
                2,
                28,
                33,
                1,
                10,
                51,
                17,
                30,
                22,
                35,
                34,
                46,
                6,
                21,
                1,
                47,
                13,
                38,
                45,
                16,
                43,
                20,
                41,
                42,
                48,
                1,
                15,
                1
            ],
            "tempo_execucao": 116.49243092536926,
            "carga_por_rota": [
                142,
                149,
                157,
                158,
                150,
                21
            ]
        },
        {
            "execucao": 9,
            "distancia": 567.793570674455,
            "rota": [
                1,
                2,
                9,
                29,
                4,
                37,
                36,
                21,
                60,
                23,
                33,
                12,
                1,
                10,
                3,
                30,
                22,
                17,
                51,
                35,
                31,
                40,
                11,
                18,
                5,
                1,
                14,
                47,
                48,
                42,
                52,
                41,
                20,
                43,
                45,
                16,
                38,
                1,
                13,
                19,
                7,
                15,
                26,
                25,
                44,
                1,
                8,
                24,
                27,
                49,
                28,
                32,
                46,
                34,
                50,
                39,
                1,
                6,
                1
            ],
            "tempo_execucao": 110.50739884376526,
            "carga_por_rota": [
                150,
                156,
                144,
                155,
                151,
                21
            ]
        },
        {
            "execucao": 10,
            "distancia": 615.0458083841346,
            "rota": [
                1,
                33,
                21,
                37,
                36,
                30,
                22,
                51,
                59,
                35,
                10,
                17,
                12,
                1,
                31,
                2,
                23,
                4,
                60,
                3,
                39,
                11,
                40,
                50,
                6,
                1,
                26,
                15,
                25,
                44,
                24,
                8,
                54,
                27,
                9,
                32,
                1,
                49,
                28,
                29,
                47,
                56,
                7,
                42,
                20,
                41,
                52,
                45,
                46,
                34,
                1,
                16,
                13,
                14,
                18,
                38,
                43,
                5,
                19,
                1,
                48,
                1
            ],
            "tempo_execucao": 115.09917855262756,
            "carga_por_rota": [
                158,
                153,
                146,
                158,
                137,
                25
            ]
        },
        {
            "execucao": 11,
            "distancia": 585.8809499540818,
            "rota": [
                1,
                38,
                18,
                43,
                45,
                16,
                46,
                34,
                58,
                31,
                35,
                10,
                39,
                47,
                1,
                24,
                33,
                22,
                30,
                21,
                36,
                37,
                4,
                2,
                27,
                8,
                44,
                1,
                25,
                26,
                12,
                51,
                17,
                59,
                50,
                11,
                40,
                6,
                1,
                13,
                3,
                19,
                14,
                41,
                20,
                1,
                42,
                5,
                48,
                15,
                7,
                49,
                9,
                32,
                1,
                29,
                23,
                28,
                1
            ],
            "tempo_execucao": 110.76839017868042,
            "carga_por_rota": [
                160,
                153,
                140,
                139,
                148,
                37
            ]
        },
        {
            "execucao": 12,
            "distancia": 551.4122095399699,
            "rota": [
                1,
                21,
                36,
                37,
                4,
                29,
                32,
                57,
                49,
                8,
                44,
                7,
                1,
                27,
                28,
                33,
                2,
                23,
                9,
                57,
                24,
                25,
                26,
                15,
                1,
                14,
                13,
                48,
                5,
                43,
                20,
                41,
                42,
                1,
                19,
                40,
                58,
                47,
                12,
                39,
                10,
                51,
                17,
                30,
                22,
                1,
                35,
                31,
                11,
                50,
                3,
                56,
                18,
                38,
                45,
                16,
                46,
                1,
                34,
                6,
                1
            ],
            "tempo_execucao": 103.97163009643555,
            "carga_por_rota": [
                154,
                147,
                142,
                144,
                146,
                44
            ]
        },
        {
            "execucao": 13,
            "distancia": 608.6042996422289,
            "rota": [
                1,
                9,
                27,
                24,
                7,
                2,
                57,
                32,
                29,
                30,
                22,
                17,
                51,
                50,
                1,
                44,
                54,
                33,
                3,
                21,
                36,
                37,
                4,
                23,
                49,
                28,
                1,
                8,
                25,
                15,
                26,
                19,
                5,
                38,
                1,
                48,
                14,
                47,
                6,
                56,
                16,
                46,
                45,
                43,
                20,
                41,
                1,
                42,
                12,
                39,
                10,
                35,
                31,
                11,
                40,
                18,
                1,
                13,
                34,
                1
            ],
            "tempo_execucao": 115.96609497070312,
            "carga_por_rota": [
                150,
                160,
                137,
                139,
                139,
                52
            ]
        },
        {
            "execucao": 14,
            "distancia": 549.9458645128586,
            "rota": [
                1,
                38,
                16,
                34,
                46,
                45,
                18,
                5,
                48,
                7,
                25,
                8,
                44,
                1,
                24,
                9,
                29,
                32,
                27,
                28,
                26,
                47,
                6,
                50,
                1,
                11,
                40,
                31,
                35,
                10,
                39,
                12,
                49,
                13,
                1,
                43,
                20,
                41,
                42,
                14,
                19,
                53,
                15,
                17,
                1,
                22,
                30,
                21,
                36,
                37,
                4,
                3,
                23,
                2,
                33,
                51,
                1
            ],
            "tempo_execucao": 111.57931804656982,
            "carga_por_rota": [
                160,
                158,
                155,
                156,
                148
            ]
        },
        {
            "execucao": 15,
            "distancia": 615.4855645999128,
            "rota": [
                1,
                5,
                14,
                42,
                41,
                43,
                20,
                52,
                45,
                46,
                34,
                16,
                1,
                31,
                50,
                11,
                22,
                3,
                21,
                37,
                36,
                4,
                1,
                29,
                32,
                2,
                17,
                9,
                57,
                27,
                8,
                24,
                25,
                49,
                7,
                47,
                1,
                12,
                6,
                39,
                10,
                40,
                35,
                51,
                59,
                23,
                33,
                28,
                30,
                1,
                15,
                26,
                19,
                48,
                18,
                38,
                13,
                1,
                44,
                1
            ],
            "tempo_execucao": 112.10059976577759,
            "carga_por_rota": [
                147,
                147,
                159,
                157,
                156,
                11
            ]
        },
        {
            "execucao": 16,
            "distancia": 598.6764570444581,
            "rota": [
                1,
                7,
                8,
                27,
                32,
                29,
                23,
                4,
                60,
                17,
                10,
                39,
                1,
                19,
                3,
                60,
                37,
                36,
                21,
                30,
                22,
                51,
                1,
                35,
                31,
                47,
                40,
                58,
                12,
                33,
                2,
                26,
                15,
                1,
                25,
                24,
                9,
                49,
                53,
                43,
                28,
                13,
                6,
                1,
                50,
                11,
                34,
                46,
                16,
                45,
                38,
                18,
                53,
                44,
                14,
                42,
                1,
                41,
                20,
                5,
                48,
                1
            ],
            "tempo_execucao": 116.26692700386047,
            "carga_por_rota": [
                131,
                146,
                151,
                144,
                155,
                50
            ]
        },
        {
            "execucao": 17,
            "distancia": 596.3271452479011,
            "rota": [
                1,
                7,
                2,
                23,
                29,
                4,
                37,
                36,
                60,
                3,
                12,
                33,
                1,
                14,
                13,
                48,
                5,
                19,
                15,
                1,
                49,
                28,
                32,
                24,
                25,
                8,
                27,
                9,
                21,
                30,
                22,
                1,
                17,
                51,
                10,
                44,
                18,
                38,
                16,
                34,
                46,
                45,
                43,
                20,
                41,
                1,
                42,
                26,
                50,
                59,
                47,
                39,
                35,
                31,
                11,
                40,
                1,
                6,
                1
            ],
            "tempo_execucao": 113.58179020881653,
            "carga_por_rota": [
                144,
                148,
                160,
                147,
                157,
                21
            ]
        },
        {
            "execucao": 18,
            "distancia": 612.7765533401414,
            "rota": [
                1,
                28,
                9,
                32,
                2,
                33,
                12,
                13,
                48,
                1,
                26,
                23,
                29,
                4,
                60,
                37,
                36,
                21,
                17,
                51,
                22,
                30,
                1,
                3,
                15,
                47,
                50,
                35,
                31,
                40,
                34,
                1,
                46,
                16,
                43,
                18,
                42,
                52,
                11,
                10,
                39,
                6,
                38,
                45,
                20,
                41,
                1,
                14,
                5,
                19,
                49,
                27,
                8,
                44,
                25,
                24,
                1,
                7,
                1
            ],
            "tempo_execucao": 111.09262895584106,
            "carga_por_rota": [
                141,
                156,
                156,
                156,
                153,
                15
            ]
        },
        {
            "execucao": 19,
            "distancia": 576.0239080891349,
            "rota": [
                1,
                18,
                45,
                46,
                16,
                38,
                5,
                52,
                41,
                20,
                43,
                42,
                14,
                53,
                7,
                1,
                44,
                25,
                24,
                8,
                27,
                9,
                49,
                28,
                47,
                6,
                1,
                13,
                19,
                26,
                15,
                3,
                1,
                33,
                2,
                23,
                29,
                32,
                4,
                37,
                36,
                21,
                60,
                30,
                12,
                1,
                34,
                50,
                11,
                40,
                31,
                51,
                22,
                35,
                17,
                10,
                1,
                39,
                48,
                1
            ],
            "tempo_execucao": 114.81330108642578,
            "carga_por_rota": [
                151,
                144,
                149,
                144,
                149,
                40
            ]
        },
        {
            "execucao": 20,
            "distancia": 565.2945010823062,
            "rota": [
                1,
                48,
                19,
                15,
                25,
                44,
                24,
                7,
                1,
                21,
                49,
                8,
                54,
                27,
                9,
                32,
                29,
                22,
                30,
                17,
                1,
                3,
                26,
                47,
                56,
                38,
                16,
                34,
                46,
                45,
                18,
                52,
                41,
                20,
                1,
                42,
                14,
                5,
                43,
                12,
                39,
                10,
                51,
                35,
                1,
                31,
                40,
                11,
                50,
                6,
                13,
                28,
                2,
                23,
                4,
                37,
                1,
                36,
                33,
                1
            ],
            "tempo_execucao": 107.84551239013672,
            "carga_por_rota": [
                139,
                148,
                150,
                153,
                158,
                29
            ]
        }
    ]
}