{
    "arquivo": "E-n23-k3",
    "media_distancia": 605.9746048046919,
    "desvio_padrao_distancia": 30.74233192772304,
    "minimo_distancia": 546.1606246548718,
    "maximo_distancia": 652.4393094723932,
    "media_tempo": 24.702398014068603,
    "desvio_padrao_tempo": 2.2481990528091464,
    "execucao_melhor_rota": 13,
    "capacidade_veiculo": 4500,
    "resultados_execucoes": [
        {
            "execucao": 1,
            "distancia": 617.5552323793038,
            "rota": [
                1,
                23,
                18,
                15,
                31,
                16,
                17,
                4,
                3,
                2,
                1,
                11,
                19,
                1,
                20,
                13,
                8,
                22,
                5,
                6,
                9,
                10,
                14,
                12,
                7,
                1,
                21,
                1
            ],
            "tempo_execucao": 29.19520902633667,
            "carga_por_rota": [
                1344,
                4220,
                4125,
                500
            ]
        },
        {
            "execucao": 2,
            "distancia": 590.1032740598653,
            "rota": [
                1,
                14,
                11,
                1,
                6,
                13,
                7,
                2,
                3,
                4,
                17,
                16,
                18,
                23,
                15,
                21,
                20,
                19,
                22,
                5,
                9,
                1,
                8,
                12,
                10,
                1
            ],
            "tempo_execucao": 27.383694410324097,
            "carga_por_rota": [
                4350,
                4164,
                1675
            ]
        },
        {
            "execucao": 3,
            "distancia": 593.5015833392804,
            "rota": [
                1,
                11,
                14,
                1,
                18,
                13,
                28,
                20,
                21,
                23,
                30,
                15,
                16,
                17,
                4,
                3,
                2,
                7,
                12,
                10,
                1,
                8,
                19,
                22,
                25,
                6,
                5,
                9,
                1
            ],
            "tempo_execucao": 24.43021059036255,
            "carga_por_rota": [
                4350,
                4244,
                1595
            ]
        },
        {
            "execucao": 4,
            "distancia": 640.215189008069,
            "rota": [
                1,
                13,
                12,
                14,
                10,
                8,
                9,
                6,
                5,
                26,
                22,
                27,
                23,
                30,
                18,
                15,
                2,
                7,
                1,
                16,
                19,
                20,
                27,
                21,
                17,
                4,
                3,
                1,
                11,
                1
            ],
            "tempo_execucao": 27.05443525314331,
            "carga_por_rota": [
                4475,
                1614,
                4100
            ]
        },
        {
            "execucao": 5,
            "distancia": 629.258434925491,
            "rota": [
                1,
                7,
                11,
                1,
                10,
                12,
                8,
                9,
                6,
                14,
                29,
                2,
                3,
                4,
                16,
                17,
                15,
                18,
                31,
                23,
                21,
                1,
                20,
                19,
                22,
                25,
                13,
                5,
                1
            ],
            "tempo_execucao": 26.860281705856323,
            "carga_por_rota": [
                4275,
                4219,
                1695
            ]
        },
        {
            "execucao": 6,
            "distancia": 652.4393094723932,
            "rota": [
                1,
                18,
                15,
                1,
                11,
                12,
                7,
                1,
                14,
                10,
                6,
                5,
                2,
                3,
                4,
                17,
                16,
                23,
                21,
                20,
                19,
                22,
                8,
                1,
                9,
                13,
                1
            ],
            "tempo_execucao": 23.331305503845215,
            "carga_por_rota": [
                750,
                4500,
                4489,
                450
            ]
        },
        {
            "execucao": 7,
            "distancia": 617.3084990960776,
            "rota": [
                1,
                11,
                14,
                1,
                6,
                28,
                23,
                21,
                20,
                19,
                22,
                5,
                9,
                8,
                12,
                7,
                2,
                3,
                4,
                16,
                17,
                18,
                15,
                1,
                13,
                10,
                1
            ],
            "tempo_execucao": 26.605480670928955,
            "carga_por_rota": [
                4350,
                4439,
                1400
            ]
        },
        {
            "execucao": 8,
            "distancia": 609.8431281641848,
            "rota": [
                1,
                13,
                3,
                4,
                17,
                16,
                21,
                30,
                23,
                18,
                15,
                2,
                7,
                12,
                14,
                10,
                8,
                1,
                6,
                9,
                5,
                22,
                25,
                20,
                19,
                1,
                11,
                1
            ],
            "tempo_execucao": 26.259137868881226,
            "carga_por_rota": [
                4244,
                1845,
                4100
            ]
        },
        {
            "execucao": 9,
            "distancia": 624.4466627502618,
            "rota": [
                1,
                19,
                21,
                18,
                16,
                15,
                31,
                17,
                4,
                12,
                10,
                6,
                5,
                9,
                26,
                22,
                8,
                1,
                23,
                30,
                11,
                1,
                20,
                3,
                32,
                2,
                7,
                14,
                13,
                1
            ],
            "tempo_execucao": 22.952230215072632,
            "carga_por_rota": [
                4480,
                4175,
                1534
            ]
        },
        {
            "execucao": 10,
            "distancia": 547.4377340010841,
            "rota": [
                1,
                8,
                6,
                5,
                9,
                14,
                10,
                29,
                7,
                2,
                3,
                4,
                17,
                16,
                18,
                15,
                31,
                13,
                1,
                22,
                12,
                29,
                21,
                23,
                20,
                19,
                1,
                11,
                1
            ],
            "tempo_execucao": 26.29850697517395,
            "carga_por_rota": [
                4394,
                1695,
                4100
            ]
        },
        {
            "execucao": 11,
            "distancia": 584.6228474872339,
            "rota": [
                1,
                19,
                20,
                21,
                23,
                31,
                16,
                17,
                4,
                3,
                2,
                7,
                29,
                10,
                9,
                6,
                5,
                22,
                1,
                15,
                31,
                14,
                1,
                11,
                18,
                1,
                8,
                12,
                13,
                1
            ],
            "tempo_execucao": 22.997201204299927,
            "carga_por_rota": [
                4214,
                750,
                4350,
                875
            ]
        },
        {
            "execucao": 12,
            "distancia": 569.6299427097264,
            "rota": [
                1,
                2,
                4,
                17,
                16,
                18,
                30,
                23,
                21,
                20,
                19,
                28,
                10,
                6,
                5,
                9,
                8,
                1,
                22,
                13,
                12,
                14,
                29,
                7,
                3,
                15,
                1,
                11,
                1
            ],
            "tempo_execucao": 23.407052993774414,
            "carga_por_rota": [
                4380,
                1709,
                4100
            ]
        },
        {
            "execucao": 13,
            "distancia": 546.1606246548718,
            "rota": [
                1,
                11,
                14,
                1,
                22,
                8,
                10,
                26,
                6,
                5,
                9,
                12,
                13,
                7,
                2,
                3,
                17,
                16,
                4,
                15,
                1,
                18,
                23,
                21,
                20,
                19,
                1
            ],
            "tempo_execucao": 22.788243055343628,
            "carga_por_rota": [
                4350,
                4294,
                1545
            ]
        },
        {
            "execucao": 14,
            "distancia": 639.779707371288,
            "rota": [
                1,
                19,
                9,
                11,
                1,
                22,
                8,
                5,
                6,
                10,
                14,
                15,
                16,
                17,
                4,
                3,
                2,
                7,
                12,
                1,
                20,
                13,
                28,
                18,
                23,
                21,
                1
            ],
            "tempo_execucao": 19.72426414489746,
            "carga_por_rota": [
                4370,
                4094,
                1725
            ]
        },
        {
            "execucao": 15,
            "distancia": 593.0739194536142,
            "rota": [
                1,
                19,
                21,
                23,
                20,
                27,
                22,
                5,
                6,
                9,
                26,
                8,
                10,
                14,
                7,
                2,
                1,
                18,
                13,
                12,
                29,
                3,
                4,
                17,
                16,
                15,
                1,
                11,
                1
            ],
            "tempo_execucao": 22.942058086395264,
            "carga_por_rota": [
                4420,
                1669,
                4100
            ]
        },
        {
            "execucao": 16,
            "distancia": 591.2491409954478,
            "rota": [
                1,
                19,
                22,
                8,
                9,
                26,
                5,
                6,
                10,
                12,
                14,
                7,
                2,
                32,
                16,
                18,
                23,
                21,
                1,
                20,
                15,
                17,
                4,
                3,
                32,
                13,
                1,
                11,
                1
            ],
            "tempo_execucao": 22.86240792274475,
            "carga_por_rota": [
                4445,
                1644,
                4100
            ]
        },
        {
            "execucao": 17,
            "distancia": 635.5355816595877,
            "rota": [
                1,
                13,
                11,
                1,
                22,
                8,
                12,
                14,
                10,
                6,
                5,
                9,
                7,
                2,
                3,
                4,
                23,
                21,
                1,
                20,
                18,
                17,
                16,
                15,
                19,
                1
            ],
            "tempo_execucao": 23.348435401916504,
            "carga_por_rota": [
                4400,
                4069,
                1720
            ]
        },
        {
            "execucao": 18,
            "distancia": 634.6690355300932,
            "rota": [
                1,
                3,
                4,
                23,
                30,
                21,
                20,
                19,
                1,
                11,
                1,
                10,
                9,
                5,
                6,
                8,
                22,
                25,
                14,
                12,
                7,
                2,
                17,
                16,
                15,
                13,
                1,
                18,
                1
            ],
            "tempo_execucao": 26.259653091430664,
            "carga_por_rota": [
                1439,
                4100,
                4400,
                250
            ]
        },
        {
            "execucao": 19,
            "distancia": 632.5926303889314,
            "rota": [
                1,
                11,
                14,
                1,
                20,
                12,
                29,
                8,
                9,
                22,
                5,
                6,
                7,
                3,
                4,
                2,
                17,
                15,
                16,
                18,
                23,
                21,
                19,
                1,
                13,
                10,
                1
            ],
            "tempo_execucao": 26.426117658615112,
            "carga_por_rota": [
                4350,
                4439,
                1400
            ]
        },
        {
            "execucao": 20,
            "distancia": 570.069618647033,
            "rota": [
                1,
                9,
                5,
                6,
                10,
                14,
                29,
                4,
                17,
                16,
                18,
                23,
                21,
                20,
                19,
                13,
                1,
                15,
                8,
                1,
                11,
                22,
                25,
                12,
                1,
                7,
                2,
                3,
                1
            ],
            "tempo_execucao": 22.92203450202942,
            "carga_por_rota": [
                4455,
                850,
                4500,
                384
            ]
        }
    ]
}